{
  "/blog-ee9": {
    "__comp": "a6aa9e1f",
    "__context": {
      "plugin": "ae48e8b2"
    },
    "sidebar": "814f3328",
    "items": [
      {
        "content": "8ade110d"
      }
    ],
    "metadata": "b2b675dd"
  },
  "/blog/archive-f1a": {
    "__comp": "9e4087bc",
    "__context": {
      "plugin": "ae48e8b2"
    },
    "archive": "b2f554cd"
  },
  "/blog/blog-3a8": {
    "__comp": "ccc49370",
    "__context": {
      "plugin": "ae48e8b2"
    },
    "sidebar": "814f3328",
    "content": "f0ae8b9e"
  },
  "/blog/tags-69b": {
    "__comp": "01a85c17",
    "__context": {
      "plugin": "ae48e8b2"
    },
    "sidebar": "814f3328",
    "tags": "a7023ddc"
  },
  "/blog/tags/hello-290": {
    "__comp": "6875c492",
    "__context": {
      "plugin": "ae48e8b2"
    },
    "sidebar": "814f3328",
    "items": [
      {
        "content": "8ade110d"
      }
    ],
    "tag": "30a24c52",
    "listMetadata": "66406991"
  },
  "/markdown-page-26d": {
    "__comp": "1f391b9e",
    "__context": {
      "plugin": "d6153e84"
    },
    "content": "393be207"
  },
  "/docs-91e": {
    "__comp": "5e95c892",
    "__context": {
      "plugin": "a485ca0f"
    }
  },
  "/docs-1ab": {
    "__comp": "a7bd4aaa",
    "version": "935f2afb"
  },
  "/docs-f07": {
    "__comp": "a94703ab"
  },
  "/docs/build/contracts-eb5": {
    "__comp": "17896441",
    "content": "1ca28016"
  },
  "/docs/build/etf_js-6ca": {
    "__comp": "17896441",
    "content": "ce59ce01"
  },
  "/docs/build/etf_sdk-bc9": {
    "__comp": "17896441",
    "content": "ed5782d4"
  },
  "/docs/build/getting_started-1e8": {
    "__comp": "17896441",
    "content": "1c6fe862"
  },
  "/docs/build/validator-747": {
    "__comp": "17896441",
    "content": "7ddff167"
  },
  "/docs/category/build-59e": {
    "__comp": "14eb3368",
    "categoryGeneratedIndex": "63ebcbce"
  },
  "/docs/category/learn-b98": {
    "__comp": "14eb3368",
    "categoryGeneratedIndex": "09873bbf"
  },
  "/docs/category/play-cb3": {
    "__comp": "14eb3368",
    "categoryGeneratedIndex": "c8b58e45"
  },
  "/docs/examples/contract_examples-9e7": {
    "__comp": "17896441",
    "content": "b1e95ceb"
  },
  "/docs/examples/getting_started-938": {
    "__comp": "17896441",
    "content": "070ed66b"
  },
  "/docs/examples/timelock_auction-d76": {
    "__comp": "17896441",
    "content": "edb80855"
  },
  "/docs/intro-aed": {
    "__comp": "17896441",
    "content": "0e384e19"
  },
  "/docs/learn/crypto/delayed_transactions-d01": {
    "__comp": "17896441",
    "content": "5dd6b6ee"
  },
  "/docs/learn/crypto/timelock_encryption-b60": {
    "__comp": "17896441",
    "content": "d477c2c5"
  },
  "/docs/learn/etf-pfg-b68": {
    "__comp": "17896441",
    "content": "959f78f4"
  },
  "/-9fe": {
    "__comp": "c4f5d8e4",
    "__context": {
      "plugin": "d6153e84"
    },
    "config": "5e9f5e1a"
  }
}